[
  {
    "name": "Bench Press",
    "equipment": "Barbell",
    "bodyPart": "Chest"
  },
  {
    "name": "Squat",
    "equipment": "Barbell",
    "bodyPart": "Legs"
  },
  {
    "name": "Deadlift",
    "equipment": "Barbell",
    "bodyPart": "Back"
  },
  {
    "name": "Pull-Up",
    "equipment": "Bodyweight",
    "bodyPart": "Back"
  },
  {
    "name": "Push-Up",
    "equipment": "Bodyweight",
    "bodyPart": "Chest"
  },
  {
    "name": "Bicep Curl",
    "equipment": "Dumbbell",
    "bodyPart": "Arms"
  },
  {
    "name": "Tricep Dip",
    "equipment": "Bodyweight",
    "bodyPart": "Arms"
  },
  {
    "name": "Lunges",
    "equipment": "Bodyweight",
    "bodyPart": "Legs"
  },
  {
    "name": "Plank",
    "equipment": "Bodyweight",
    "bodyPart": "Core"
  },
  {
    "name": "Shoulder Press",
    "equipment": "Dumbbell",
    "bodyPart": "Shoulders"
  },
  {
    "name": "Leg Press",
    "equipment": "Machine",
    "bodyPart": "Legs"
  },
  {
    "name": "Lat Pulldown",
    "equipment": "Machine",
    "bodyPart": "Back"
  },
  {
    "name": "Chest Fly",
    "equipment": "Machine",
    "bodyPart": "Chest"
  },
  {
    "name": "Calf Raise",
    "equipment": "Bodyweight",
    "bodyPart": "Legs"
  },
  {
    "name": "Russian Twist",
    "equipment": "Bodyweight",
    "bodyPart": "Core"
  },
  {
    "name": "Leg Raise",
    "equipment": "Bodyweight",
    "bodyPart": "Core"
  },
  {
    "name": "Seated Row",
    "equipment": "Machine",
    "bodyPart": "Back"
  },
  {
    "name": "Dumbbell Fly",
    "equipment": "Dumbbell",
    "bodyPart": "Chest"
  },
  {
    "name": "Lateral Raise",
    "equipment": "Dumbbell",
    "bodyPart": "Shoulders"
  },
  {
    "name": "Front Raise",
    "equipment": "Dumbbell",
    "bodyPart": "Shoulders"
  },
  {
    "name": "Mountain Climber",
    "equipment": "Bodyweight",
    "bodyPart": "Core"
  },
  {
    "name": "Burpee",
    "equipment": "Bodyweight",
    "bodyPart": "Full Body"
  },
  {
    "name": "Kettlebell Swing",
    "equipment": "Kettlebell",
    "bodyPart": "Full Body"
  },
  {
    "name": "Box Jump",
    "equipment": "Bodyweight",
    "bodyPart": "Legs"
  },
  {
    "name": "Cable Row",
    "equipment": "Cable Machine",
    "bodyPart": "Back"
  },
  {
    "name": "Face Pull",
    "equipment": "Cable Machine",
    "bodyPart": "Shoulders"
  },
  {
    "name": "Skull Crusher",
    "equipment": "Dumbbell",
    "bodyPart": "Arms"
  },
  {
    "name": "Leg Extension",
    "equipment": "Machine",
    "bodyPart": "Legs"
  },
  {
    "name": "Leg Curl",
    "equipment": "Machine",
    "bodyPart": "Legs"
  },
  {
    "name": "Hip Thrust",
    "equipment": "Barbell",
    "bodyPart": "Legs"
  },
  {
    "name": "Glute Bridge",
    "equipment": "Bodyweight",
    "bodyPart": "Legs"
  },
  {
    "name": "Plank Shoulder Taps",
    "equipment": "Bodyweight",
    "bodyPart": "Core"
  },
  {
    "name": "Side Plank",
    "equipment": "Bodyweight",
    "bodyPart": "Core"
  },
  {
    "name": "Reverse Crunch",
    "equipment": "Bodyweight",
    "bodyPart": "Core"
  },
  {
    "name": "Cable Tricep Pushdown",
    "equipment": "Cable Machine",
    "bodyPart": "Arms"
  },
  {
    "name": "Dumbbell Tricep Kickback",
    "equipment": "Dumbbell",
    "bodyPart": "Arms"
  },
  {
    "name": "Dumbbell Shoulder Press",
    "equipment": "Dumbbell",
    "bodyPart": "Shoulders"
  },
  {
    "name": "Arnold Press",
    "equipment": "Dumbbell",
    "bodyPart": "Shoulders"
  },
  {
    "name": "Cable Lateral Raise",
    "equipment": "Cable Machine",
    "bodyPart": "Shoulders"
  },
  {
    "name": "Standing Calf Raise",
    "equipment": "Machine",
    "bodyPart": "Legs"
  },
  {
    "name": "Seated Calf Raise",
    "equipment": "Machine",
    "bodyPart": "Legs"
  },
  {
    "name": "Dumbbell Step-Up",
    "equipment": "Dumbbell",
    "bodyPart": "Legs"
  },
  {
    "name": "Cable Chest Fly",
    "equipment": "Cable Machine",
    "bodyPart": "Chest"
  },
  {
    "name": "Incline Bench Press",
    "equipment": "Barbell",
    "bodyPart": "Chest"
  },
  {
    "name": "Decline Bench Press",
    "equipment": "Barbell",
    "bodyPart": "Chest"
  },
  {
    "name": "Chest Press Machine",
    "equipment": "Machine",
    "bodyPart": "Chest"
  },
  {
    "name": "Smith Machine Squat",
    "equipment": "Smith Machine",
    "bodyPart": "Legs"
  },
  {
    "name": "Smith Machine Deadlift",
    "equipment": "Smith Machine",
    "bodyPart": "Back"
  },
  {
    "name": "Smith Machine Bench Press",
    "equipment": "Smith Machine",
    "bodyPart": "Chest"
  },
  {
    "name": "Cable Bicep Curl",
    "equipment": "Cable Machine",
    "bodyPart": "Arms"
  },
  {
    "name": "Cable Lateral Pulldown",
    "equipment": "Cable Machine",
    "bodyPart": "Back"
  },
  {
    "name": "Barbell Curl",
    "equipment": "Barbell",
    "bodyPart": "Arms"
  },
  {
    "name": "Barbell Preacher Curl",
    "equipment": "Barbell",
    "bodyPart": "Arms"
  },
  {
    "name": "Cable Curl",
    "equipment": "Cable Machine",
    "bodyPart": "Arms"
  },
  {
    "name": "Dumbbell Curl",
    "equipment": "Dumbbell",
    "bodyPart": "Arms"
  },
  {
    "name": "Hammer Curl",
    "equipment": "Dumbbell",
    "bodyPart": "Arms"
  },
  {
    "name": "Incline Dumbbell Curl",
    "equipment": "Dumbbell",
    "bodyPart": "Arms"
  },
  {
    "name": "Machine Bicep Curl",
    "equipment": "Machine",
    "bodyPart": "Arms"
  },
  {
    "name": "Cable Hammer Curl",
    "equipment": "Cable Machine",
    "bodyPart": "Arms"
  },
  {
    "name": "Dumbbell Preacher Curl",
    "equipment": "Dumbbell",
    "bodyPart": "Arms"
  },
  {
    "name": "Barbell Reverse Curl",
    "equipment": "Barbell",
    "bodyPart": "Arms"
  },
  {
    "name": "Barbell Skullcrusher",
    "equipment": "Barbell",
    "bodyPart": "Arms"
  },
  {
    "name": "Cable Tricep Extension",
    "equipment": "Cable Machine",
    "bodyPart": "Arms"
  },
  {
    "name": "Dumbbell Tricep Kickback",
    "equipment": "Dumbbell",
    "bodyPart": "Arms"
  },
  {
    "name": "Machine Tricep Extension",
    "equipment": "Machine",
    "bodyPart": "Arms"
  },
  {
    "name": "Cable Overhead Tricep Extension",
    "equipment": "Cable Machine",
    "bodyPart": "Arms"
  },
  {
    "name": "Barbell Close-Grip Bench Press",
    "equipment": "Barbell",
    "bodyPart": "Arms"
  },
  {
    "name": "Dumbbell Overhead Tricep Extension",
    "equipment": "Dumbbell",
    "bodyPart": "Arms"
  },
  {
    "name": "Cable Tricep Pushdown",
    "equipment": "Cable Machine",
    "bodyPart": "Arms"
  },
  {
    "name": "Barbell Lying Tricep Extension",
    "equipment": "Barbell",
    "bodyPart": "Arms"
  },
  {
    "name": "Dumbbell Skullcrusher",
    "equipment": "Dumbbell",
    "bodyPart": "Arms"
  },
  {
    "name": "Barbell Shoulder Press",
    "equipment": "Barbell",
    "bodyPart": "Shoulders"
  },
  {
    "name": "Dumbbell Shoulder Press",
    "equipment": "Dumbbell",
    "bodyPart": "Shoulders"
  },
  {
    "name": "Cable Lateral Raise",
    "equipment": "Cable Machine",
    "bodyPart": "Shoulders"
  },
  {
    "name": "Machine Shoulder Press",
    "equipment": "Machine",
    "bodyPart": "Shoulders"
  },
  {
    "name": "Barbell Upright Row",
    "equipment": "Barbell",
    "bodyPart": "Shoulders"
  },
  {
    "name": "Dumbbell Lateral Raise",
    "equipment": "Dumbbell",
    "bodyPart": "Shoulders"
  },
  {
    "name": "Cable Front Raise",
    "equipment": "Cable Machine",
    "bodyPart": "Shoulders"
  },
  {
    "name": "Machine Lateral Raise",
    "equipment": "Machine",
    "bodyPart": "Shoulders"
  },
  {
    "name": "Dumbbell Front Raise",
    "equipment": "Dumbbell",
    "bodyPart": "Shoulders"
  },
  {
    "name": "Barbell Front Raise",
    "equipment": "Barbell",
    "bodyPart": "Shoulders"
  },
  {
    "name": "Cable Rear Delt Fly",
    "equipment": "Cable Machine",
    "bodyPart": "Shoulders"
  },
  {
    "name": "Barbell Bench Press",
    "equipment": "Barbell",
    "bodyPart": "Chest"
  },
  {
    "name": "Dumbbell Bench Press",
    "equipment": "Dumbbell",
    "bodyPart": "Chest"
  },
  {
    "name": "Cables Chest Fly",
    "equipment": "Cables",
    "bodyPart": "Chest"
  },
  {
    "name": "Machine Chest Press",
    "equipment": "Machine",
    "bodyPart": "Chest"
  },
  {
    "name": "Barbell Incline Bench Press",
    "equipment": "Barbell",
    "bodyPart": "Chest"
  },
  {
    "name": "Dumbbell Incline Bench Press",
    "equipment": "Dumbbell",
    "bodyPart": "Chest"
  },
  {
    "name": "Cables Crossover",
    "equipment": "Cables",
    "bodyPart": "Chest"
  },
  {
    "name": "Machine Chest Fly",
    "equipment": "Machine",
    "bodyPart": "Chest"
  },
  {
    "name": "Barbell Decline Bench Press",
    "equipment": "Barbell",
    "bodyPart": "Chest"
  },
  {
    "name": "Dumbbell Decline Bench Press",
    "equipment": "Dumbbell",
    "bodyPart": "Chest"
  },
  {
    "name": "Barbell Row",
    "equipment": "Barbell",
    "bodyPart": "Back"
  },
  {
    "name": "Dumbbell Row",
    "equipment": "Dumbbell",
    "bodyPart": "Back"
  },
  {
    "name": "Cables Row",
    "equipment": "Cables",
    "bodyPart": "Back"
  },
  {
    "name": "Machine Row",
    "equipment": "Machine",
    "bodyPart": "Back"
  },
  {
    "name": "Barbell Deadlift",
    "equipment": "Barbell",
    "bodyPart": "Back"
  },
  {
    "name": "Dumbbell Pullover",
    "equipment": "Dumbbell",
    "bodyPart": "Back"
  },
  {
    "name": "Cables Lat Pulldown",
    "equipment": "Cables",
    "bodyPart": "Back"
  },
  {
    "name": "Machine Lat Pulldown",
    "equipment": "Machine",
    "bodyPart": "Back"
  },
  {
    "name": "Barbell Shrug",
    "equipment": "Barbell",
    "bodyPart": "Back"
  },
  {
    "name": "Dumbbell Shrug",
    "equipment": "Dumbbell",
    "bodyPart": "Back"
  },
  {
    "name": "Cables Face Pull",
    "equipment": "Cables",
    "bodyPart": "Back"
  },
  {
    "name": "Barbell Squat",
    "equipment": "Barbell",
    "bodyPart": "Legs"
  },
  {
    "name": "Dumbbell Lunge",
    "equipment": "Dumbbell",
    "bodyPart": "Legs"
  },
  {
    "name": "Cables Leg Extension",
    "equipment": "Cables",
    "bodyPart": "Legs"
  },
  {
    "name": "Machine Leg Extension",
    "equipment": "Machine",
    "bodyPart": "Legs"
  },
  {
    "name": "Barbell Romanian Deadlift",
    "equipment": "Barbell",
    "bodyPart": "Legs"
  },
  {
    "name": "Dumbbell Squat",
    "equipment": "Dumbbell",
    "bodyPart": "Legs"
  },
  {
    "name": "Cables Leg Curl",
    "equipment": "Cables",
    "bodyPart": "Legs"
  },
  {
    "name": "Machine Leg Curl",
    "equipment": "Machine",
    "bodyPart": "Legs"
  },
  {
    "name": "Barbell Lunge",
    "equipment": "Barbell",
    "bodyPart": "Legs"
  },
  {
    "name": "Dumbbell Step-Up",
    "equipment": "Dumbbell",
    "bodyPart": "Legs"
  },
  {
    "name": "Machine Leg Press",
    "equipment": "Machine",
    "bodyPart": "Legs"
  },
  {
    "name": "Cables Crunch",
    "equipment": "Cables",
    "bodyPart": "Core"
  },
  {
    "name": "Machine Crunch",
    "equipment": "Machine",
    "bodyPart": "Core"
  },
  {
    "name": "Dumbbell Side Bend",
    "equipment": "Dumbbell",
    "bodyPart": "Core"
  },
  {
    "name": "Barbell Rollout",
    "equipment": "Barbell",
    "bodyPart": "Core"
  },
  {
    "name": "Cables Woodchopper",
    "equipment": "Cables",
    "bodyPart": "Core"
  },
  {
    "name": "Dumbbell Russian Twist",
    "equipment": "Dumbbell",
    "bodyPart": "Core"
  },
  {
    "name": "Machine Ab Rotation",
    "equipment": "Machine",
    "bodyPart": "Core"
  },
  {
    "name": "Hej",
    "equipment": "Hej",
    "bodyPart": "Hej"
  },
  {
    "name": "Hej2",
    "equipment": "Hej2",
    "bodyPart": "Hej2"
  },
  {
    "name": "Hej3",
    "equipment": "Hej3",
    "bodyPart": "Hej3"
  }
]